k3ng/__init__.py
k3ng/k3ng.py
k3ng_rotator_python-2.0.0.dist-info/LICENSE
k3ng_rotator_python-2.0.0.dist-info/METADATA
k3ng_rotator_python-2.0.0.dist-info/WHEEL
k3ng_rotator_python-2.0.0.dist-info/RECORD
